MANIFEST.in
README.md
setup.cfg
setup.py
bin/seriesview-start-backend
seriesview/__init__.py
seriesview/serialize_wrapper.py
seriesview/version.py
seriesview.egg-info/PKG-INFO
seriesview.egg-info/SOURCES.txt
seriesview.egg-info/dependency_links.txt
seriesview.egg-info/requires.txt
seriesview.egg-info/top_level.txt
seriesview/MultiPanelView/MultiPanelView.py
seriesview/MultiPanelView/__init__.py
seriesview/backend/__init__.py
seriesview/backend/start_backend.py
seriesview/backend/start_backend_cli.py
seriesview/backend/task_function_ids.json
seriesview/config/__init__.py
seriesview/config/job_cache.py
seriesview/config/job_handler.py
seriesview/svseries/SVSeries.py
seriesview/svseries/SVSeriesSegment.py
seriesview/svseries/__init__.py
seriesview/tasks/__init__.py
seriesview/tasks/get_array.py
seriesview/tasks/get_series_manifest.py
seriesview/tasks/python_package_version.py